{"name":"dsmeta_consolidamentorendicontattivitaprogettoora_default","relations":{"FK_consolidamentorendicontattivitaprogettoora_rendicontattivitaprogettoorapersonaleview_idrendicontattivitaprogettoora":{"parentTable":"rendicontattivitaprogettoorapersonaleview","parentCols":"idrendicontattivitaprogettoora","childTable":"consolidamentorendicontattivitaprogettoora","childCols":"idrendicontattivitaprogettoora"}},"tables":{"rendicontattivitaprogettoorapersonaleview":{"name":"rendicontattivitaprogettoorapersonaleview","key":"idrendicontattivitaprogetto,idrendicontattivitaprogettoora,idworkpackage","columns":{"dropdown_title":{"caption":"dropdown_title","name":"dropdown_title","ctype":"String","allowDbNull":false,"isDenyNull":false,"isDenyZero":false,"forPosting":"dropdown_title"},"idprogetto":{"caption":"idprogetto","name":"idprogetto","ctype":"Int32","allowDbNull":true,"isDenyNull":false,"isDenyZero":false,"forPosting":"idprogetto"},"idrendicontattivitaprogetto":{"caption":"idrendicontattivitaprogetto","name":"idrendicontattivitaprogetto","ctype":"Int32","allowDbNull":false,"isDenyNull":false,"isDenyZero":false,"forPosting":"idrendicontattivitaprogetto"},"idrendicontattivitaprogettoora":{"caption":"idrendicontattivitaprogettoora","name":"idrendicontattivitaprogettoora","ctype":"Int32","allowDbNull":false,"isDenyNull":false,"isDenyZero":false,"forPosting":"idrendicontattivitaprogettoora"},"idworkpackage":{"caption":"idworkpackage","name":"idworkpackage","ctype":"Int32","allowDbNull":false,"isDenyNull":false,"isDenyZero":false,"forPosting":"idworkpackage"},"progetto_titolobreve":{"caption":"progetto_titolobreve","name":"progetto_titolobreve","ctype":"String","allowDbNull":true,"isDenyNull":false,"isDenyZero":false,"forPosting":"progetto_titolobreve"},"rendicontattivitaprogetto_description":{"caption":"rendicontattivitaprogetto_description","name":"rendicontattivitaprogetto_description","ctype":"String","allowDbNull":true,"isDenyNull":false,"isDenyZero":false,"forPosting":"rendicontattivitaprogetto_description"},"rendicontattivitaprogettoora_ct":{"caption":"rendicontattivitaprogettoora_ct","name":"rendicontattivitaprogettoora_ct","ctype":"DateTime","allowDbNull":false,"isDenyNull":false,"isDenyZero":false,"forPosting":"rendicontattivitaprogettoora_ct"},"rendicontattivitaprogettoora_cu":{"caption":"rendicontattivitaprogettoora_cu","name":"rendicontattivitaprogettoora_cu","ctype":"String","allowDbNull":false,"isDenyNull":false,"isDenyZero":false,"forPosting":"rendicontattivitaprogettoora_cu"},"rendicontattivitaprogettoora_data":{"caption":"rendicontattivitaprogettoora_data","name":"rendicontattivitaprogettoora_data","ctype":"DateTime","allowDbNull":true,"isDenyNull":false,"isDenyZero":false,"forPosting":"rendicontattivitaprogettoora_data"},"rendicontattivitaprogettoora_idconsolidamento":{"caption":"rendicontattivitaprogettoora_idconsolidamento","name":"rendicontattivitaprogettoora_idconsolidamento","ctype":"Int32","allowDbNull":true,"isDenyNull":false,"isDenyZero":false,"forPosting":"rendicontattivitaprogettoora_idconsolidamento"},"rendicontattivitaprogettoora_idreg":{"caption":"rendicontattivitaprogettoora_idreg","name":"rendicontattivitaprogettoora_idreg","ctype":"Int32","allowDbNull":true,"isDenyNull":false,"isDenyZero":false,"forPosting":"rendicontattivitaprogettoora_idreg"},"rendicontattivitaprogettoora_idsal":{"caption":"rendicontattivitaprogettoora_idsal","name":"rendicontattivitaprogettoora_idsal","ctype":"Int32","allowDbNull":true,"isDenyNull":false,"isDenyZero":false,"forPosting":"rendicontattivitaprogettoora_idsal"},"rendicontattivitaprogettoora_lt":{"caption":"rendicontattivitaprogettoora_lt","name":"rendicontattivitaprogettoora_lt","ctype":"DateTime","allowDbNull":false,"isDenyNull":false,"isDenyZero":false,"forPosting":"rendicontattivitaprogettoora_lt"},"rendicontattivitaprogettoora_lu":{"caption":"rendicontattivitaprogettoora_lu","name":"rendicontattivitaprogettoora_lu","ctype":"String","allowDbNull":false,"isDenyNull":false,"isDenyZero":false,"forPosting":"rendicontattivitaprogettoora_lu"},"rendicontattivitaprogettoora_ore":{"caption":"rendicontattivitaprogettoora_ore","name":"rendicontattivitaprogettoora_ore","ctype":"Int32","allowDbNull":true,"isDenyNull":false,"isDenyZero":false,"forPosting":"rendicontattivitaprogettoora_ore"},"sal_start":{"caption":"sal_start","name":"sal_start","ctype":"DateTime","allowDbNull":true,"isDenyNull":false,"isDenyZero":false,"forPosting":"sal_start"},"sal_stop":{"caption":"sal_stop","name":"sal_stop","ctype":"DateTime","allowDbNull":true,"isDenyNull":false,"isDenyZero":false,"forPosting":"sal_stop"},"workpackage_raggruppamento":{"caption":"workpackage_raggruppamento","name":"workpackage_raggruppamento","ctype":"String","allowDbNull":true,"isDenyNull":false,"isDenyZero":false,"forPosting":"workpackage_raggruppamento"},"workpackage_title":{"caption":"workpackage_title","name":"workpackage_title","ctype":"String","allowDbNull":true,"isDenyNull":false,"isDenyZero":false,"forPosting":"workpackage_title"}},"rows":[],"tableForReading":"rendicontattivitaprogettoorapersonaleview","tableForWriting":"rendicontattivitaprogettoorapersonaleview","isCached":null,"isTemporaryTable":false,"autoIncrementColumns":{},"staticFilter":null,"skipSecurity":false,"skipInsertCopy":false,"realTable":"","viewTable":"","denyClear":null,"defaults":{"dropdown_title":null,"idprogetto":null,"idrendicontattivitaprogetto":null,"idrendicontattivitaprogettoora":null,"idworkpackage":null,"progetto_titolobreve":null,"rendicontattivitaprogetto_description":null,"rendicontattivitaprogettoora_ct":null,"rendicontattivitaprogettoora_cu":null,"rendicontattivitaprogettoora_data":null,"rendicontattivitaprogettoora_idconsolidamento":null,"rendicontattivitaprogettoora_idreg":null,"rendicontattivitaprogettoora_idsal":null,"rendicontattivitaprogettoora_lt":null,"rendicontattivitaprogettoora_lu":null,"rendicontattivitaprogettoora_ore":null,"sal_start":null,"sal_stop":null,"workpackage_raggruppamento":null,"workpackage_title":null},"orderBy":null},"consolidamentorendicontattivitaprogettoora":{"name":"consolidamentorendicontattivitaprogettoora","key":"idconsolidamento,idrendicontattivitaprogettoora","columns":{"ct":{"caption":"ct","name":"ct","ctype":"DateTime","allowDbNull":true,"isDenyNull":false,"isDenyZero":false,"forPosting":"ct"},"cu":{"caption":"cu","name":"cu","ctype":"String","allowDbNull":true,"isDenyNull":false,"isDenyZero":false,"forPosting":"cu"},"idconsolidamento":{"caption":"idconsolidamento","name":"idconsolidamento","ctype":"Int32","allowDbNull":false,"isDenyNull":false,"isDenyZero":false,"forPosting":"idconsolidamento"},"idrendicontattivitaprogettoora":{"caption":"idrendicontattivitaprogettoora","name":"idrendicontattivitaprogettoora","ctype":"Int32","allowDbNull":false,"isDenyNull":false,"isDenyZero":false,"forPosting":"idrendicontattivitaprogettoora"},"lt":{"caption":"lt","name":"lt","ctype":"DateTime","allowDbNull":true,"isDenyNull":false,"isDenyZero":false,"forPosting":"lt"},"lu":{"caption":"lu","name":"lu","ctype":"String","allowDbNull":true,"isDenyNull":false,"isDenyZero":false,"forPosting":"lu"}},"rows":[],"tableForReading":"consolidamentorendicontattivitaprogettoora","tableForWriting":"consolidamentorendicontattivitaprogettoora","isCached":null,"isTemporaryTable":false,"autoIncrementColumns":{},"staticFilter":null,"skipSecurity":false,"skipInsertCopy":false,"realTable":"","viewTable":"","denyClear":null,"defaults":{"ct":null,"cu":null,"idconsolidamento":null,"idrendicontattivitaprogettoora":null,"lt":null,"lu":null},"orderBy":null}}}