{"name":"dsmeta_consolidamento_default","relations":{"FK_consolidamentorendicontattivitaprogettoora_consolidamento_idconsolidamento":{"parentTable":"consolidamento","parentCols":"idconsolidamento","childTable":"consolidamentorendicontattivitaprogettoora","childCols":"idconsolidamento"},"FK_consolidamentorendicontattivitaprogettoora_rendicontattivitaprogettoora_idrendicontattivitaprogettoora":{"parentTable":"rendicontattivitaprogettoora","parentCols":"idrendicontattivitaprogettoora","childTable":"consolidamentorendicontattivitaprogettoora","childCols":"idrendicontattivitaprogettoora"},"FK_rendicontattivitaprogettoora_workpackage_idworkpackage":{"parentTable":"workpackage","parentCols":"idworkpackage","childTable":"rendicontattivitaprogettoora","childCols":"idworkpackage"},"FK_rendicontattivitaprogettoora_sal_idsal":{"parentTable":"sal","parentCols":"idsal","childTable":"rendicontattivitaprogettoora","childCols":"idsal"},"FK_rendicontattivitaprogettoora_rendicontattivitaprogetto_idrendicontattivitaprogetto":{"parentTable":"rendicontattivitaprogetto","parentCols":"idrendicontattivitaprogetto","childTable":"rendicontattivitaprogettoora","childCols":"idrendicontattivitaprogetto"},"FK_rendicontattivitaprogettoora_progetto_idprogetto":{"parentTable":"progetto","parentCols":"idprogetto","childTable":"rendicontattivitaprogettoora","childCols":"idprogetto"},"FK_consolidamento_registry_idreg":{"parentTable":"registry","parentCols":"idreg","childTable":"consolidamento","childCols":"idreg"}},"tables":{"workpackage":{"name":"workpackage","key":"idprogetto,idworkpackage","columns":{"idprogetto":{"caption":"idprogetto","name":"idprogetto","ctype":"Int32","allowDbNull":false,"isDenyNull":false,"isDenyZero":false,"forPosting":"idprogetto"},"idworkpackage":{"caption":"idworkpackage","name":"idworkpackage","ctype":"Int32","allowDbNull":false,"isDenyNull":false,"isDenyZero":false,"forPosting":"idworkpackage"},"raggruppamento":{"caption":"raggruppamento","name":"raggruppamento","ctype":"String","allowDbNull":true,"isDenyNull":false,"isDenyZero":false,"forPosting":"raggruppamento"},"title":{"caption":"title","name":"title","ctype":"String","allowDbNull":false,"isDenyNull":false,"isDenyZero":false,"forPosting":"title"}},"rows":[],"tableForReading":"workpackage","tableForWriting":"workpackage","isCached":null,"isTemporaryTable":false,"autoIncrementColumns":{},"staticFilter":null,"skipSecurity":false,"skipInsertCopy":false,"realTable":"","viewTable":"","denyClear":null,"defaults":{"idprogetto":null,"idworkpackage":null,"raggruppamento":null,"title":null},"orderBy":null},"sal":{"name":"sal","key":"idprogetto,idsal","columns":{"datablocco":{"caption":"datablocco","name":"datablocco","ctype":"DateTime","allowDbNull":true,"isDenyNull":false,"isDenyZero":false,"forPosting":"datablocco"},"idprogetto":{"caption":"idprogetto","name":"idprogetto","ctype":"Int32","allowDbNull":false,"isDenyNull":false,"isDenyZero":false,"forPosting":"idprogetto"},"idsal":{"caption":"idsal","name":"idsal","ctype":"Int32","allowDbNull":false,"isDenyNull":false,"isDenyZero":false,"forPosting":"idsal"},"start":{"caption":"start","name":"start","ctype":"DateTime","allowDbNull":true,"isDenyNull":false,"isDenyZero":false,"forPosting":"start"},"stop":{"caption":"stop","name":"stop","ctype":"DateTime","allowDbNull":true,"isDenyNull":false,"isDenyZero":false,"forPosting":"stop"}},"rows":[],"tableForReading":"sal","tableForWriting":"sal","isCached":null,"isTemporaryTable":false,"autoIncrementColumns":{},"staticFilter":null,"skipSecurity":false,"skipInsertCopy":false,"realTable":"","viewTable":"","denyClear":null,"defaults":{"datablocco":null,"idprogetto":null,"idsal":null,"start":null,"stop":null},"orderBy":null},"rendicontattivitaprogetto":{"name":"rendicontattivitaprogetto","key":"idprogetto,idreg,idrendicontattivitaprogetto,idworkpackage","columns":{"description":{"caption":"description","name":"description","ctype":"String","allowDbNull":true,"isDenyNull":false,"isDenyZero":false,"forPosting":"description"},"idprogetto":{"caption":"idprogetto","name":"idprogetto","ctype":"Int32","allowDbNull":false,"isDenyNull":false,"isDenyZero":false,"forPosting":"idprogetto"},"idreg":{"caption":"idreg","name":"idreg","ctype":"Int32","allowDbNull":false,"isDenyNull":false,"isDenyZero":false,"forPosting":"idreg"},"idrendicontattivitaprogetto":{"caption":"idrendicontattivitaprogetto","name":"idrendicontattivitaprogetto","ctype":"Int32","allowDbNull":false,"isDenyNull":false,"isDenyZero":false,"forPosting":"idrendicontattivitaprogetto"},"idworkpackage":{"caption":"idworkpackage","name":"idworkpackage","ctype":"Int32","allowDbNull":false,"isDenyNull":false,"isDenyZero":false,"forPosting":"idworkpackage"}},"rows":[],"tableForReading":"rendicontattivitaprogetto","tableForWriting":"rendicontattivitaprogetto","isCached":null,"isTemporaryTable":false,"autoIncrementColumns":{},"staticFilter":null,"skipSecurity":false,"skipInsertCopy":false,"realTable":"","viewTable":"","denyClear":null,"defaults":{"description":null,"idprogetto":null,"idreg":null,"idrendicontattivitaprogetto":null,"idworkpackage":null},"orderBy":null},"progetto":{"name":"progetto","key":"idprogetto","columns":{"idprogetto":{"caption":"idprogetto","name":"idprogetto","ctype":"Int32","allowDbNull":false,"isDenyNull":false,"isDenyZero":false,"forPosting":"idprogetto"},"start":{"caption":"start","name":"start","ctype":"DateTime","allowDbNull":true,"isDenyNull":false,"isDenyZero":false,"forPosting":"start"},"stop":{"caption":"stop","name":"stop","ctype":"DateTime","allowDbNull":true,"isDenyNull":false,"isDenyZero":false,"forPosting":"stop"},"titolobreve":{"caption":"titolobreve","name":"titolobreve","ctype":"String","allowDbNull":true,"isDenyNull":false,"isDenyZero":false,"forPosting":"titolobreve"}},"rows":[],"tableForReading":"progetto","tableForWriting":"progetto","isCached":null,"isTemporaryTable":false,"autoIncrementColumns":{},"staticFilter":null,"skipSecurity":false,"skipInsertCopy":false,"realTable":"","viewTable":"","denyClear":null,"defaults":{"idprogetto":null,"start":null,"stop":null,"titolobreve":null},"orderBy":null},"rendicontattivitaprogettoora":{"name":"rendicontattivitaprogettoora","key":"idprogetto,idreg,idrendicontattivitaprogetto,idrendicontattivitaprogettoora,idworkpackage","columns":{"!titleancestor":{"caption":"!titleancestor","name":"!titleancestor","ctype":"String","allowDbNull":true,"isDenyNull":false,"isDenyZero":false,"forPosting":"!titleancestor"},"ct":{"caption":"ct","name":"ct","ctype":"DateTime","allowDbNull":false,"isDenyNull":false,"isDenyZero":false,"forPosting":"ct"},"cu":{"caption":"cu","name":"cu","ctype":"String","allowDbNull":false,"isDenyNull":false,"isDenyZero":false,"forPosting":"cu"},"data":{"caption":"data","name":"data","ctype":"DateTime","allowDbNull":true,"isDenyNull":false,"isDenyZero":false,"forPosting":"data"},"idconsolidamento":{"caption":"idconsolidamento","name":"idconsolidamento","ctype":"Int32","allowDbNull":true,"isDenyNull":false,"isDenyZero":false,"forPosting":"idconsolidamento"},"idprogetto":{"caption":"idprogetto","name":"idprogetto","ctype":"Int32","allowDbNull":false,"isDenyNull":false,"isDenyZero":false,"forPosting":"idprogetto"},"idreg":{"caption":"idreg","name":"idreg","ctype":"Int32","allowDbNull":false,"isDenyNull":false,"isDenyZero":false,"forPosting":"idreg"},"idrendicontattivitaprogetto":{"caption":"idrendicontattivitaprogetto","name":"idrendicontattivitaprogetto","ctype":"Int32","allowDbNull":false,"isDenyNull":false,"isDenyZero":false,"forPosting":"idrendicontattivitaprogetto"},"idrendicontattivitaprogettoora":{"caption":"idrendicontattivitaprogettoora","name":"idrendicontattivitaprogettoora","ctype":"Int32","allowDbNull":false,"isDenyNull":false,"isDenyZero":false,"forPosting":"idrendicontattivitaprogettoora"},"idsal":{"caption":"idsal","name":"idsal","ctype":"Int32","allowDbNull":true,"isDenyNull":false,"isDenyZero":false,"forPosting":"idsal"},"idworkpackage":{"caption":"idworkpackage","name":"idworkpackage","ctype":"Int32","allowDbNull":false,"isDenyNull":false,"isDenyZero":false,"forPosting":"idworkpackage"},"lt":{"caption":"lt","name":"lt","ctype":"DateTime","allowDbNull":false,"isDenyNull":false,"isDenyZero":false,"forPosting":"lt"},"lu":{"caption":"lu","name":"lu","ctype":"String","allowDbNull":false,"isDenyNull":false,"isDenyZero":false,"forPosting":"lu"},"ore":{"caption":"ore","name":"ore","ctype":"Int32","allowDbNull":true,"isDenyNull":false,"isDenyZero":false,"forPosting":"ore"}},"rows":[],"tableForReading":"rendicontattivitaprogettoora","tableForWriting":"rendicontattivitaprogettoora","isCached":null,"isTemporaryTable":false,"autoIncrementColumns":{},"staticFilter":null,"skipSecurity":false,"skipInsertCopy":false,"realTable":"","viewTable":"","denyClear":null,"defaults":{"!titleancestor":null,"ct":null,"cu":null,"data":null,"idconsolidamento":null,"idprogetto":null,"idreg":null,"idrendicontattivitaprogetto":null,"idrendicontattivitaprogettoora":null,"idsal":null,"idworkpackage":null,"lt":null,"lu":null,"ore":null},"orderBy":null},"consolidamentorendicontattivitaprogettoora":{"name":"consolidamentorendicontattivitaprogettoora","key":"idconsolidamento,idrendicontattivitaprogettoora","columns":{"ct":{"caption":"ct","name":"ct","ctype":"DateTime","allowDbNull":true,"isDenyNull":false,"isDenyZero":false,"forPosting":"ct"},"cu":{"caption":"cu","name":"cu","ctype":"String","allowDbNull":true,"isDenyNull":false,"isDenyZero":false,"forPosting":"cu"},"idconsolidamento":{"caption":"idconsolidamento","name":"idconsolidamento","ctype":"Int32","allowDbNull":false,"isDenyNull":false,"isDenyZero":false,"forPosting":"idconsolidamento"},"idrendicontattivitaprogettoora":{"caption":"idrendicontattivitaprogettoora","name":"idrendicontattivitaprogettoora","ctype":"Int32","allowDbNull":false,"isDenyNull":false,"isDenyZero":false,"forPosting":"idrendicontattivitaprogettoora"},"lt":{"caption":"lt","name":"lt","ctype":"DateTime","allowDbNull":true,"isDenyNull":false,"isDenyZero":false,"forPosting":"lt"},"lu":{"caption":"lu","name":"lu","ctype":"String","allowDbNull":true,"isDenyNull":false,"isDenyZero":false,"forPosting":"lu"},"!idrendicontattivitaprogettoora_progetto_titolobreve":{"caption":"!idrendicontattivitaprogettoora_progetto_titolobreve","name":"!idrendicontattivitaprogettoora_progetto_titolobreve","ctype":"String","allowDbNull":true,"isDenyNull":false,"isDenyZero":false,"forPosting":"!idrendicontattivitaprogettoora_progetto_titolobreve"},"!idrendicontattivitaprogettoora_progetto_start":{"caption":"!idrendicontattivitaprogettoora_progetto_start","name":"!idrendicontattivitaprogettoora_progetto_start","ctype":"DateTime","allowDbNull":true,"isDenyNull":false,"isDenyZero":false,"forPosting":"!idrendicontattivitaprogettoora_progetto_start"},"!idrendicontattivitaprogettoora_progetto_stop":{"caption":"!idrendicontattivitaprogettoora_progetto_stop","name":"!idrendicontattivitaprogettoora_progetto_stop","ctype":"DateTime","allowDbNull":true,"isDenyNull":false,"isDenyZero":false,"forPosting":"!idrendicontattivitaprogettoora_progetto_stop"},"!idrendicontattivitaprogettoora_workpackage_raggruppamento":{"caption":"!idrendicontattivitaprogettoora_workpackage_raggruppamento","name":"!idrendicontattivitaprogettoora_workpackage_raggruppamento","ctype":"String","allowDbNull":true,"isDenyNull":false,"isDenyZero":false,"forPosting":"!idrendicontattivitaprogettoora_workpackage_raggruppamento"},"!idrendicontattivitaprogettoora_workpackage_title":{"caption":"!idrendicontattivitaprogettoora_workpackage_title","name":"!idrendicontattivitaprogettoora_workpackage_title","ctype":"String","allowDbNull":true,"isDenyNull":false,"isDenyZero":false,"forPosting":"!idrendicontattivitaprogettoora_workpackage_title"},"!idrendicontattivitaprogettoora_rendicontattivitaprogetto_description":{"caption":"!idrendicontattivitaprogettoora_rendicontattivitaprogetto_description","name":"!idrendicontattivitaprogettoora_rendicontattivitaprogetto_description","ctype":"String","allowDbNull":true,"isDenyNull":false,"isDenyZero":false,"forPosting":"!idrendicontattivitaprogettoora_rendicontattivitaprogetto_description"},"!idrendicontattivitaprogettoora_rendicontattivitaprogettoora_data":{"caption":"!idrendicontattivitaprogettoora_rendicontattivitaprogettoora_data","name":"!idrendicontattivitaprogettoora_rendicontattivitaprogettoora_data","ctype":"DateTime","allowDbNull":true,"isDenyNull":false,"isDenyZero":false,"forPosting":"!idrendicontattivitaprogettoora_rendicontattivitaprogettoora_data"},"!idrendicontattivitaprogettoora_rendicontattivitaprogettoora_ore":{"caption":"!idrendicontattivitaprogettoora_rendicontattivitaprogettoora_ore","name":"!idrendicontattivitaprogettoora_rendicontattivitaprogettoora_ore","ctype":"Int32","allowDbNull":true,"isDenyNull":false,"isDenyZero":false,"forPosting":"!idrendicontattivitaprogettoora_rendicontattivitaprogettoora_ore"},"!idrendicontattivitaprogettoora_sal_start":{"caption":"!idrendicontattivitaprogettoora_sal_start","name":"!idrendicontattivitaprogettoora_sal_start","ctype":"DateTime","allowDbNull":true,"isDenyNull":false,"isDenyZero":false,"forPosting":"!idrendicontattivitaprogettoora_sal_start"},"!idrendicontattivitaprogettoora_sal_stop":{"caption":"!idrendicontattivitaprogettoora_sal_stop","name":"!idrendicontattivitaprogettoora_sal_stop","ctype":"DateTime","allowDbNull":true,"isDenyNull":false,"isDenyZero":false,"forPosting":"!idrendicontattivitaprogettoora_sal_stop"},"!idrendicontattivitaprogettoora_sal_datablocco":{"caption":"!idrendicontattivitaprogettoora_sal_datablocco","name":"!idrendicontattivitaprogettoora_sal_datablocco","ctype":"DateTime","allowDbNull":true,"isDenyNull":false,"isDenyZero":false,"forPosting":"!idrendicontattivitaprogettoora_sal_datablocco"}},"rows":[],"tableForReading":"consolidamentorendicontattivitaprogettoora","tableForWriting":"consolidamentorendicontattivitaprogettoora","isCached":null,"isTemporaryTable":false,"autoIncrementColumns":{},"staticFilter":null,"skipSecurity":false,"skipInsertCopy":false,"realTable":"","viewTable":"","denyClear":null,"defaults":{"ct":null,"cu":null,"idconsolidamento":null,"idrendicontattivitaprogettoora":null,"lt":null,"lu":null,"!idrendicontattivitaprogettoora_progetto_titolobreve":null,"!idrendicontattivitaprogettoora_progetto_start":null,"!idrendicontattivitaprogettoora_progetto_stop":null,"!idrendicontattivitaprogettoora_workpackage_raggruppamento":null,"!idrendicontattivitaprogettoora_workpackage_title":null,"!idrendicontattivitaprogettoora_rendicontattivitaprogetto_description":null,"!idrendicontattivitaprogettoora_rendicontattivitaprogettoora_data":null,"!idrendicontattivitaprogettoora_rendicontattivitaprogettoora_ore":null,"!idrendicontattivitaprogettoora_sal_start":null,"!idrendicontattivitaprogettoora_sal_stop":null,"!idrendicontattivitaprogettoora_sal_datablocco":null},"orderBy":null},"registry":{"name":"registry","key":"idreg","columns":{"active":{"caption":"active","name":"active","ctype":"String","allowDbNull":false,"isDenyNull":false,"isDenyZero":false,"forPosting":"active"},"idreg":{"caption":"idreg","name":"idreg","ctype":"Int32","allowDbNull":false,"isDenyNull":false,"isDenyZero":false,"forPosting":"idreg"},"title":{"caption":"title","name":"title","ctype":"String","allowDbNull":false,"isDenyNull":false,"isDenyZero":false,"forPosting":"title"}},"rows":[],"tableForReading":"registry","tableForWriting":"registry","isCached":null,"isTemporaryTable":false,"autoIncrementColumns":{},"staticFilter":null,"skipSecurity":false,"skipInsertCopy":false,"realTable":"","viewTable":"","denyClear":null,"defaults":{"active":null,"idreg":null,"title":null},"orderBy":null},"consolidamento":{"name":"consolidamento","key":"idconsolidamento","columns":{"ct":{"caption":"ct","name":"ct","ctype":"DateTime","allowDbNull":true,"isDenyNull":false,"isDenyZero":false,"forPosting":"ct"},"cu":{"caption":"cu","name":"cu","ctype":"String","allowDbNull":true,"isDenyNull":false,"isDenyZero":false,"forPosting":"cu"},"idconsolidamento":{"caption":"idconsolidamento","name":"idconsolidamento","ctype":"Int32","allowDbNull":false,"isDenyNull":false,"isDenyZero":false,"forPosting":"idconsolidamento"},"idreg":{"caption":"idreg","name":"idreg","ctype":"Int32","allowDbNull":true,"isDenyNull":false,"isDenyZero":false,"forPosting":"idreg"},"lt":{"caption":"lt","name":"lt","ctype":"DateTime","allowDbNull":true,"isDenyNull":false,"isDenyZero":false,"forPosting":"lt"},"lu":{"caption":"lu","name":"lu","ctype":"String","allowDbNull":true,"isDenyNull":false,"isDenyZero":false,"forPosting":"lu"},"start":{"caption":"start","name":"start","ctype":"DateTime","allowDbNull":true,"isDenyNull":false,"isDenyZero":false,"forPosting":"start"},"stop":{"caption":"stop","name":"stop","ctype":"DateTime","allowDbNull":true,"isDenyNull":false,"isDenyZero":false,"forPosting":"stop"}},"rows":[],"tableForReading":"consolidamento","tableForWriting":"consolidamento","isCached":null,"isTemporaryTable":false,"autoIncrementColumns":{},"staticFilter":null,"skipSecurity":false,"skipInsertCopy":false,"realTable":"","viewTable":"","denyClear":null,"defaults":{"ct":null,"cu":null,"idconsolidamento":null,"idreg":null,"lt":null,"lu":null,"start":null,"stop":null},"orderBy":null}}}